<?xml version="1.0" encoding="utf-8"?>
<!DOCTYPE hibernate-mapping PUBLIC "-//Hibernate/Hibernate Mapping DTD 3.0//EN"
"http://www.hibernate.org/dtd/hibernate-mapping-3.0.dtd">
<!-- 
    Mapping file autogenerated by MyEclipse Persistence Tools
-->
<hibernate-mapping>
    <class name="com.cem.pojo.Topic" table="topic" catalog="cemsys">
        <id name="topicId" type="java.lang.String">
            <column name="topicId" length="5" />
            <generator class="assigned" />
        </id>
        <property name="topicName" type="java.lang.String">
            <column name="topicName" length="20">
                <comment>主题名称</comment>
            </column>
        </property>
        <property name="description" type="java.lang.String">
            <column name="description" length="1000">
                <comment>描述</comment>
            </column>
        </property>
        <property name="sequence" type="java.lang.String">
            <column name="sequence" length="2">
                <comment>显示顺序</comment>
            </column>
        </property>
        <property name="isDeleted" type="java.lang.String">
            <column name="isDeleted" length="1" not-null="true">
                <comment>是否删除的标志</comment>
            </column>
        </property>
    </class>
</hibernate-mapping>
