<?xml version="1.0" encoding="utf-8"?>
<!DOCTYPE hibernate-mapping PUBLIC "-//Hibernate/Hibernate Mapping DTD 3.0//EN"
"http://www.hibernate.org/dtd/hibernate-mapping-3.0.dtd">
<!-- 
    Mapping file autogenerated by MyEclipse Persistence Tools
-->
<hibernate-mapping>
    <class name="com.cem.pojo.Bbsrank" table="bbsrank" catalog="cemsys">
        <id name="rankId" type="java.lang.String">
            <column name="rankId" length="5" />
            <generator class="assigned" />
        </id>
        <property name="rankName" type="java.lang.String">
            <column name="rankName" length="20">
                <comment>等级名称</comment>
            </column>
        </property>
        <property name="icon" type="java.lang.String">
            <column name="icon" length="100">
                <comment>icon的路径</comment>
            </column>
        </property>
        <property name="isDeleted" type="java.lang.String">
            <column name="isDeleted" length="1" not-null="true">
                <comment>是否删除的标志</comment>
            </column>
        </property>
    </class>
</hibernate-mapping>
